<?xml version="1.0" encoding="UTF-8"?>
<!-- vim: set softtabstop=2 tabstop=2 shiftwidth=2 expandtab: -->
<package
    packagerversion="1.9.1" version="2.0"
    xmlns="http://pear.php.net/dtd/package-2.0"
    xmlns:tasks="http://pear.php.net/dtd/tasks-1.0"
    xmlns:xsi="http://www.w3.org/2001/XMLSchema-instance"
    xsi:schemaLocation="
        http://pear.php.net/dtd/tasks-1.0 http://pear.php.net/dtd/tasks-1.0.xsd
        http://pear.php.net/dtd/package-2.0 http://pear.php.net/dtd/package-2.0.xsd
    ">

  <name>Lousson_Record</name>
  <channel>pear.lousson.org</channel>
  <summary>Universal data records</summary>
  <description>
    The Lousson_Record package eases the creation of portable data records
    that are serializable in various formats.
  </description>

  <lead>
    <name>Mathias J. Hennig</name>
    <user>mjhennig</user>
    <email>mhennig at quirkies.org</email>
    <active>yes</active>
  </lead>
  <developer>
    <name>Attila Levai</name>
    <user>sgnl19</user>
    <email>alevai at quirkies.org</email>
    <active>yes</active>
  </developer>

  <date>2013-06-07</date>
  <time>06:48:49</time>
  <version>
    <release>0.4.0</release>
    <api>0.4</api>
  </version>
  <stability>
    <release>stable</release>
    <api>stable</api>
  </stability>
  <license uri="http://www.opensource.org/licenses/bsd-license.php">New BSD License</license>
  <notes>
    Initial release.
  </notes>

  <contents>
    <dir baseinstalldir="/" name="/">
      <file baseinstalldir="/" md5sum="6806e1510798b9cab9de6bbd992ec66d" name="/Lousson/Record/AnyRecordBuilder.php" role="php">        <tasks:replace from="@@PACKAGE_VERSION@@" to="version" type="package-info" />
        <tasks:replace from="@@PHP_DIR@@" to="php_dir" type="pear-config" />
        <tasks:replace from="@@DATA_DIR@@" to="data_dir" type="pear-config" />
      </file>
      <file baseinstalldir="/" md5sum="db988457f5fe196e549c829faa38e598" name="/Lousson/Record/AnyRecordException.php" role="php">        <tasks:replace from="@@PACKAGE_VERSION@@" to="version" type="package-info" />
        <tasks:replace from="@@PHP_DIR@@" to="php_dir" type="pear-config" />
        <tasks:replace from="@@DATA_DIR@@" to="data_dir" type="pear-config" />
      </file>
      <file baseinstalldir="/" md5sum="d7da93fe17b5633dbb4325fc02cadf45" name="/Lousson/Record/AnyRecordFactory.php" role="php">        <tasks:replace from="@@PACKAGE_VERSION@@" to="version" type="package-info" />
        <tasks:replace from="@@PHP_DIR@@" to="php_dir" type="pear-config" />
        <tasks:replace from="@@DATA_DIR@@" to="data_dir" type="pear-config" />
      </file>
      <file baseinstalldir="/" md5sum="8bcebab79b461c392d97b15a88aacaad" name="/Lousson/Record/AnyRecordHandler.php" role="php">        <tasks:replace from="@@PACKAGE_VERSION@@" to="version" type="package-info" />
        <tasks:replace from="@@PHP_DIR@@" to="php_dir" type="pear-config" />
        <tasks:replace from="@@DATA_DIR@@" to="data_dir" type="pear-config" />
      </file>
      <file baseinstalldir="/" md5sum="e048c16edf7c3c58626784e5849291e5" name="/Lousson/Record/AnyRecordParser.php" role="php">        <tasks:replace from="@@PACKAGE_VERSION@@" to="version" type="package-info" />
        <tasks:replace from="@@PHP_DIR@@" to="php_dir" type="pear-config" />
        <tasks:replace from="@@DATA_DIR@@" to="data_dir" type="pear-config" />
      </file>
      <file baseinstalldir="/" md5sum="e82e71a5991074115e79f9ce6e4fb50a" name="/Lousson/Record/Builtin/BuiltinRecordFactory.php" role="php">        <tasks:replace from="@@PACKAGE_VERSION@@" to="version" type="package-info" />
        <tasks:replace from="@@PHP_DIR@@" to="php_dir" type="pear-config" />
        <tasks:replace from="@@DATA_DIR@@" to="data_dir" type="pear-config" />
      </file>
      <file baseinstalldir="/" md5sum="4440947f803b46974acd5a78353694e3" name="/Lousson/Record/Builtin/BuiltinRecordHandler.php" role="php">        <tasks:replace from="@@PACKAGE_VERSION@@" to="version" type="package-info" />
        <tasks:replace from="@@PHP_DIR@@" to="php_dir" type="pear-config" />
        <tasks:replace from="@@DATA_DIR@@" to="data_dir" type="pear-config" />
      </file>
      <file baseinstalldir="/" md5sum="48f5fbb3a2b3d0bfaf7eaf3c3957c123" name="/Lousson/Record/Builtin/BuiltinRecordUtil.php" role="php">        <tasks:replace from="@@PACKAGE_VERSION@@" to="version" type="package-info" />
        <tasks:replace from="@@PHP_DIR@@" to="php_dir" type="pear-config" />
        <tasks:replace from="@@DATA_DIR@@" to="data_dir" type="pear-config" />
      </file>
      <file baseinstalldir="/" md5sum="9d1424bc0eca87547b98060c8d364347" name="/Lousson/Record/Builtin/Handler/BuiltinRecordHandlerJSON.php" role="php">        <tasks:replace from="@@PACKAGE_VERSION@@" to="version" type="package-info" />
        <tasks:replace from="@@PHP_DIR@@" to="php_dir" type="pear-config" />
        <tasks:replace from="@@DATA_DIR@@" to="data_dir" type="pear-config" />
      </file>
      <file baseinstalldir="/" md5sum="af5e5747402edd4393f0ab040997ff5a" name="/Lousson/Record/Builtin/Handler/BuiltinRecordHandlerPHP.php" role="php">        <tasks:replace from="@@PACKAGE_VERSION@@" to="version" type="package-info" />
        <tasks:replace from="@@PHP_DIR@@" to="php_dir" type="pear-config" />
        <tasks:replace from="@@DATA_DIR@@" to="data_dir" type="pear-config" />
      </file>
      <file baseinstalldir="/" md5sum="52a2afeb1f3e373872a11533249e2e48" name="/Lousson/Record/Builtin/Parser/BuiltinRecordParserINI.php" role="php">        <tasks:replace from="@@PACKAGE_VERSION@@" to="version" type="package-info" />
        <tasks:replace from="@@PHP_DIR@@" to="php_dir" type="pear-config" />
        <tasks:replace from="@@DATA_DIR@@" to="data_dir" type="pear-config" />
      </file>
      <file baseinstalldir="/" md5sum="f5546c0e648e1193b2051d89bfba9eeb" name="/Lousson/Record/Error/InvalidRecordError.php" role="php">        <tasks:replace from="@@PACKAGE_VERSION@@" to="version" type="package-info" />
        <tasks:replace from="@@PHP_DIR@@" to="php_dir" type="pear-config" />
        <tasks:replace from="@@DATA_DIR@@" to="data_dir" type="pear-config" />
      </file>
      <file baseinstalldir="/" md5sum="9d25b777dea3c0cb9b56dfbec0bd766c" name="/Lousson/Record/Error/RuntimeRecordError.php" role="php">        <tasks:replace from="@@PACKAGE_VERSION@@" to="version" type="package-info" />
        <tasks:replace from="@@PHP_DIR@@" to="php_dir" type="pear-config" />
        <tasks:replace from="@@DATA_DIR@@" to="data_dir" type="pear-config" />
      </file>
      <file baseinstalldir="/" md5sum="6bd061f4621f6b0fa8c5e92e8c686fde" name="/Lousson/Record/Generic/GenericRecordBuilder.php" role="php">        <tasks:replace from="@@PACKAGE_VERSION@@" to="version" type="package-info" />
        <tasks:replace from="@@PHP_DIR@@" to="php_dir" type="pear-config" />
        <tasks:replace from="@@DATA_DIR@@" to="data_dir" type="pear-config" />
      </file>
      <file baseinstalldir="/" md5sum="b0211168849e2a055814a49b73f05bc5" name="/Lousson/Record/Generic/GenericRecordFactory.php" role="php">        <tasks:replace from="@@PACKAGE_VERSION@@" to="version" type="package-info" />
        <tasks:replace from="@@PHP_DIR@@" to="php_dir" type="pear-config" />
        <tasks:replace from="@@DATA_DIR@@" to="data_dir" type="pear-config" />
      </file>
      <file baseinstalldir="/" md5sum="0ca29ff7ec31b10ed2feea55b2ea73da" name="/Lousson/Record/Generic/GenericRecordHandler.php" role="php">        <tasks:replace from="@@PACKAGE_VERSION@@" to="version" type="package-info" />
        <tasks:replace from="@@PHP_DIR@@" to="php_dir" type="pear-config" />
        <tasks:replace from="@@DATA_DIR@@" to="data_dir" type="pear-config" />
      </file>
      <file baseinstalldir="/" md5sum="2ef85e2d308a1b08354bfb51349c90eb" name="/Lousson/Record/Generic/GenericRecordParser.php" role="php">        <tasks:replace from="@@PACKAGE_VERSION@@" to="version" type="package-info" />
        <tasks:replace from="@@PHP_DIR@@" to="php_dir" type="pear-config" />
        <tasks:replace from="@@DATA_DIR@@" to="data_dir" type="pear-config" />
      </file>
      <file baseinstalldir="/" md5sum="ccc6fb5613bd8e74f94e1387ff354a3b" name="/Lousson/Record/AbstractRecordFactoryTest.php" role="test">        <tasks:replace from="@@PACKAGE_VERSION@@" to="version" type="package-info" />
        <tasks:replace from="@@PHP_DIR@@" to="php_dir" type="pear-config" />
        <tasks:replace from="@@DATA_DIR@@" to="data_dir" type="pear-config" />
      </file>
      <file baseinstalldir="/" md5sum="d81c569008af6ce7444732f729b0302f" name="/Lousson/Record/AbstractRecordHandlerTest.php" role="test">        <tasks:replace from="@@PACKAGE_VERSION@@" to="version" type="package-info" />
        <tasks:replace from="@@PHP_DIR@@" to="php_dir" type="pear-config" />
        <tasks:replace from="@@DATA_DIR@@" to="data_dir" type="pear-config" />
      </file>
      <file baseinstalldir="/" md5sum="c2c563213fdd44ef873ee4c9f5d9c703" name="/Lousson/Record/AbstractRecordTest.php" role="test">        <tasks:replace from="@@PACKAGE_VERSION@@" to="version" type="package-info" />
        <tasks:replace from="@@PHP_DIR@@" to="php_dir" type="pear-config" />
        <tasks:replace from="@@DATA_DIR@@" to="data_dir" type="pear-config" />
      </file>
      <file baseinstalldir="/" md5sum="25a81b7491918119464833a300e46483" name="/Lousson/Record/Builtin/BuiltinRecordFactoryTest.php" role="test">        <tasks:replace from="@@PACKAGE_VERSION@@" to="version" type="package-info" />
        <tasks:replace from="@@PHP_DIR@@" to="php_dir" type="pear-config" />
        <tasks:replace from="@@DATA_DIR@@" to="data_dir" type="pear-config" />
      </file>
      <file baseinstalldir="/" md5sum="304844384aacc9e28483b8ce36d5b89d" name="/Lousson/Record/Builtin/BuiltinRecordUtilTest.php" role="test">        <tasks:replace from="@@PACKAGE_VERSION@@" to="version" type="package-info" />
        <tasks:replace from="@@PHP_DIR@@" to="php_dir" type="pear-config" />
        <tasks:replace from="@@DATA_DIR@@" to="data_dir" type="pear-config" />
      </file>
      <file baseinstalldir="/" md5sum="ad823568e631fb03e6bc26c5170a7764" name="/Lousson/Record/Builtin/Handler/BuiltinRecordHandlerJSONTest.php" role="test">        <tasks:replace from="@@PACKAGE_VERSION@@" to="version" type="package-info" />
        <tasks:replace from="@@PHP_DIR@@" to="php_dir" type="pear-config" />
        <tasks:replace from="@@DATA_DIR@@" to="data_dir" type="pear-config" />
      </file>
      <file baseinstalldir="/" md5sum="366118852784bd6b643fcd95720a7f4d" name="/Lousson/Record/Builtin/Handler/BuiltinRecordHandlerPHPTest.php" role="test">        <tasks:replace from="@@PACKAGE_VERSION@@" to="version" type="package-info" />
        <tasks:replace from="@@PHP_DIR@@" to="php_dir" type="pear-config" />
        <tasks:replace from="@@DATA_DIR@@" to="data_dir" type="pear-config" />
      </file>
      <file baseinstalldir="/" md5sum="293ffff77c19e8fb8ee879fee35b8c93" name="/Lousson/Record/Builtin/Parser/BuiltinRecordParserINITest.php" role="test">        <tasks:replace from="@@PACKAGE_VERSION@@" to="version" type="package-info" />
        <tasks:replace from="@@PHP_DIR@@" to="php_dir" type="pear-config" />
        <tasks:replace from="@@DATA_DIR@@" to="data_dir" type="pear-config" />
      </file>
      <file baseinstalldir="/" md5sum="b3d8f26c2d6262832c798a6381befb68" name="/Lousson/Record/Generic/GenericRecordBuilderTest.php" role="test">        <tasks:replace from="@@PACKAGE_VERSION@@" to="version" type="package-info" />
        <tasks:replace from="@@PHP_DIR@@" to="php_dir" type="pear-config" />
        <tasks:replace from="@@DATA_DIR@@" to="data_dir" type="pear-config" />
      </file>
      <file baseinstalldir="/" md5sum="3636b4d3c69b87e6ebb0146b85bc0fb8" name="/Lousson/Record/Generic/GenericRecordFactoryBasicTest.php" role="test">        <tasks:replace from="@@PACKAGE_VERSION@@" to="version" type="package-info" />
        <tasks:replace from="@@PHP_DIR@@" to="php_dir" type="pear-config" />
        <tasks:replace from="@@DATA_DIR@@" to="data_dir" type="pear-config" />
      </file>
      <file baseinstalldir="/" md5sum="05dc43a8f2cc59f34afa256cfacd6d31" name="/Lousson/Record/Generic/GenericRecordFactoryNestedTest.php" role="test">        <tasks:replace from="@@PACKAGE_VERSION@@" to="version" type="package-info" />
        <tasks:replace from="@@PHP_DIR@@" to="php_dir" type="pear-config" />
        <tasks:replace from="@@DATA_DIR@@" to="data_dir" type="pear-config" />
      </file>
      <file baseinstalldir="/" md5sum="ff66be6cb423c2ecc5f83315a925db0f" name="/Lousson/Record/Generic/GenericRecordFactoryTest.php" role="test">        <tasks:replace from="@@PACKAGE_VERSION@@" to="version" type="package-info" />
        <tasks:replace from="@@PHP_DIR@@" to="php_dir" type="pear-config" />
        <tasks:replace from="@@DATA_DIR@@" to="data_dir" type="pear-config" />
      </file>
      <file baseinstalldir="/" md5sum="94cb45f0e90505312793255b62be1555" name="/Lousson/Record/Generic/GenericRecordHandlerTest.php" role="test">        <tasks:replace from="@@PACKAGE_VERSION@@" to="version" type="package-info" />
        <tasks:replace from="@@PHP_DIR@@" to="php_dir" type="pear-config" />
        <tasks:replace from="@@DATA_DIR@@" to="data_dir" type="pear-config" />
      </file>
      <file baseinstalldir="/" md5sum="f133584fa3b4059b9e7589bd22eac037" name="/Lousson/Record/Generic/GenericRecordParserTest.php" role="test">        <tasks:replace from="@@PACKAGE_VERSION@@" to="version" type="package-info" />
        <tasks:replace from="@@PHP_DIR@@" to="php_dir" type="pear-config" />
        <tasks:replace from="@@DATA_DIR@@" to="data_dir" type="pear-config" />
      </file>
      <file baseinstalldir="/" md5sum="97ef66b4d5a751ad364e6474162b042b" name="LICENSE.txt" role="doc">        <tasks:replace from="@@PACKAGE_VERSION@@" to="version" type="package-info" />
        <tasks:replace from="@@PHP_DIR@@" to="php_dir" type="pear-config" />
        <tasks:replace from="@@DATA_DIR@@" to="data_dir" type="pear-config" />
      </file>
      <file baseinstalldir="/" md5sum="1c51f06b69800c23746734e17f59a0e6" name="README.md" role="doc">        <tasks:replace from="@@PACKAGE_VERSION@@" to="version" type="package-info" />
        <tasks:replace from="@@PHP_DIR@@" to="php_dir" type="pear-config" />
        <tasks:replace from="@@DATA_DIR@@" to="data_dir" type="pear-config" />
      </file>

    </dir>
  </contents>

  <dependencies>
    <required>
      <php>
        <min>5.3.0</min>
      </php>
      <pearinstaller>
        <min>1.9.4</min>
      </pearinstaller>
      <package>
        <name>Autoloader</name>
        <channel>pear.phix-project.org</channel>
        <min>3.0.0</min>
        <max>3.999.9999</max>
      </package>
      <package>
        <name>Lousson_Sniffs</name>
        <channel>pear.lousson.org</channel>
        <min>0.4.0</min>
      </package>
      <package>
        <name>Lousson_Exception</name>
        <channel>pear.lousson.org</channel>
        <min>0.2.0</min>
      </package>
    </required>
  </dependencies>

  <phprelease/>

</package>
